yayi/color_utilities.py
yayi/common.py
yayi/draw.py
yayi/image_utilities.py
yayi/morpho_utilities.py
yayi/version.py
yayi/__init__.py
yayi/bin/boost_chrono-vc120-mt-1_55.dll
yayi/bin/boost_date_time-vc120-mt-1_55.dll
yayi/bin/boost_filesystem-vc120-mt-1_55.dll
yayi/bin/boost_graph-vc120-mt-1_55.dll
yayi/bin/boost_python-vc120-mt-1_55.dll
yayi/bin/boost_regex-vc120-mt-1_55.dll
yayi/bin/boost_system-vc120-mt-1_55.dll
yayi/bin/boost_thread-vc120-mt-1_55.dll
yayi/bin/YayiCommon.dll
yayi/bin/YayiCommonPython.pyd
yayi/bin/YayiDistances.dll
yayi/bin/YayiDistancesPython.pyd
yayi/bin/YayiImageCore.dll
yayi/bin/YayiImageCorePython.pyd
yayi/bin/YayiIO.dll
yayi/bin/YayiIOPython.pyd
yayi/bin/YayiLabel.dll
yayi/bin/YayiLabelPython.pyd
yayi/bin/YayiLowlevelMorphology.dll
yayi/bin/YayiLowLevelMorphologyPython.pyd
yayi/bin/YayiMeasurements.dll
yayi/bin/YayiMeasurementsPython.pyd
yayi/bin/YayiNeighborhoodProcessing.dll
yayi/bin/YayiNeighborhoodProcessingPython.pyd
yayi/bin/YayiPixelProcessing.dll
yayi/bin/YayiPixelProcessingPython.pyd
yayi/bin/YayiReconstruction.dll
yayi/bin/YayiReconstructionPython.pyd
yayi/bin/YayiSegmentation.dll
yayi/bin/YayiSegmentationPython.pyd
yayi/bin/YayiStructuringElement.dll
yayi/bin/YayiStructuringElementPython.pyd
yayi/extensions/matplotlib.py
yayi/extensions/yayi_to_numpy.py
yayi/extensions/__init__.py
yayi/tests/test_image_utilities.py
yayi/tests/test_IO.py
yayi/tests/__init__.py
yayi-0.8.8.dev0.dist-info/DESCRIPTION.rst
yayi-0.8.8.dev0.dist-info/METADATA
yayi-0.8.8.dev0.dist-info/metadata.json
yayi-0.8.8.dev0.dist-info/RECORD
yayi-0.8.8.dev0.dist-info/top_level.txt
yayi-0.8.8.dev0.dist-info/WHEEL
