Metadata-Version: 2.0
Name: yayi
Version: 0.8.8.dev0
Summary: Yayi toolbox for image processing and mathematical morphology
Home-page: http://raffi.enficiaud.free.fr
Author: Raffi Enficiaud
Author-email: raffi.enficiaud@free.fr
License: Boost Software License - Version 1.0 - August 17th, 2003
Keywords: image processing,mathematical morphology,multidimensional images,multispectral images,image segmentation,erosion,dilation,opening,closing,hit-or-miss,connected components
Platform: UNKNOWN
Classifier: Development Status :: 3 - Alpha
Classifier: Intended Audience :: Developers
Classifier: Intended Audience :: Information Technology
Classifier: Intended Audience :: Science/Research
Classifier: Operating System :: MacOS :: MacOS X
Classifier: Operating System :: Microsoft :: Windows :: Windows NT/2000
Classifier: Operating System :: POSIX :: Linux
Classifier: Programming Language :: C++
Classifier: Programming Language :: Python :: 2.7
Classifier: Topic :: Scientific/Engineering :: Image Recognition
Classifier: Topic :: Scientific/Engineering :: Mathematics
